[
  {
    "seed": 12,
    "prefix_actions": [
      "open door to east",
      "move east",
      "move east"
    ],
    "observation": "Action: look around\nYou are in the street. To the East you see a closed commercial glass door. To the West you see the backyard. \n",
    "case_id": 1,
    "closed_doors": [
      "east"
    ],
    "open_doors": [],
    "connected_dirs": [
      "west"
    ],
    "back_dir": null,
    "valid_actions": [
      "move west",
      "open door to east"
    ]
  },
  {
    "seed": 12,
    "prefix_actions": [
      "open door to east",
      "move east"
    ],
    "observation": "Action: look around\nYou are in the backyard. To the North you see a closed patio door. To the South you see a closed sliding patio door. To the East you see the street. Through an open patio door, to the West you see the kitchen. \n",
    "case_id": 2,
    "closed_doors": [
      "north",
      "south"
    ],
    "open_doors": [
      "west"
    ],
    "connected_dirs": [
      "east",
      "west"
    ],
    "back_dir": null,
    "valid_actions": [
      "move east",
      "move west",
      "open door to north",
      "open door to south"
    ]
  },
  {
    "seed": 12,
    "prefix_actions": [
      "open door to east",
      "move east",
      "move east",
      "open door to east"
    ],
    "observation": "Action: look around\nYou open the commercial glass door, revealing the supermarket. \n",
    "case_id": 3,
    "closed_doors": [],
    "open_doors": [
      "east"
    ],
    "connected_dirs": [
      "east",
      "west"
    ],
    "back_dir": null,
    "valid_actions": [
      "move east",
      "move west"
    ]
  },
  {
    "seed": 12,
    "prefix_actions": [],
    "observation": "Action: look around\nYou are in the kitchen. To the North you see a closed wood door. To the South you see a closed wood door. To the East you see a closed patio door. To the West you see a closed plain door. \n",
    "case_id": 4,
    "closed_doors": [
      "east",
      "north",
      "south",
      "west"
    ],
    "open_doors": [],
    "connected_dirs": [],
    "back_dir": null,
    "valid_actions": [
      "open door to east",
      "open door to north",
      "open door to south",
      "open door to west"
    ]
  },
  {
    "seed": 12,
    "prefix_actions": [
      "open door to east"
    ],
    "observation": "Action: look around\nYou open the patio door, revealing the backyard. \n",
    "case_id": 5,
    "closed_doors": [
      "north",
      "south",
      "west"
    ],
    "open_doors": [
      "east"
    ],
    "connected_dirs": [
      "east"
    ],
    "back_dir": null,
    "valid_actions": [
      "move east",
      "open door to north",
      "open door to south",
      "open door to west"
    ]
  },
  {
    "seed": 12,
    "prefix_actions": [
      "open door to north",
      "move north",
      "open door to east"
    ],
    "observation": "Action: look around\nYou open the wood door, revealing the corridor. \n",
    "case_id": 6,
    "closed_doors": [],
    "open_doors": [
      "east",
      "south"
    ],
    "connected_dirs": [
      "east",
      "south"
    ],
    "back_dir": null,
    "valid_actions": [
      "move east",
      "move south"
    ]
  },
  {
    "seed": 12,
    "prefix_actions": [
      "open door to west",
      "move west"
    ],
    "observation": "Action: look around\nYou are in the pantry. Through an open plain door, to the East you see the kitchen. \n",
    "case_id": 8,
    "closed_doors": [],
    "open_doors": [
      "east"
    ],
    "connected_dirs": [
      "east"
    ],
    "back_dir": "east",
    "valid_actions": [
      "move east"
    ]
  },
  {
    "seed": 12,
    "prefix_actions": [
      "open door to east",
      "move east",
      "open door to north",
      "move north",
      "move north"
    ],
    "observation": "Action: look around\nYou are in the driveway. To the South you see the corridor. \n",
    "case_id": 9,
    "closed_doors": [],
    "open_doors": [],
    "connected_dirs": [
      "south"
    ],
    "back_dir": "south",
    "valid_actions": [
      "move south"
    ]
  }
]